<annotation>
	<folder>images</folder>
	<filename>215.jpg</filename>
	<path>C:\Users\ahmet\OneDrive\Masaüstü\Yeni klasör (2)\data\images\215.jpg</path>
	<source>
		<database>Unknown</database>
	</source>
	<size>
		<width>600</width>
		<height>600</height>
		<depth>3</depth>
	</size>
	<segmented>0</segmented>
	<object>
		<name>car</name>
		<pose>Unspecified</pose>
		<truncated>0</truncated>
		<difficult>0</difficult>
		<bndbox>
			<xmin>16</xmin>
			<ymin>76</ymin>
			<xmax>42</xmax>
			<ymax>100</ymax>
		</bndbox>
	</object>
	<object>
		<name>car</name>
		<pose>Unspecified</pose>
		<truncated>0</truncated>
		<difficult>0</difficult>
		<bndbox>
			<xmin>14</xmin>
			<ymin>131</ymin>
			<xmax>67</xmax>
			<ymax>172</ymax>
		</bndbox>
	</object>
	<object>
		<name>car</name>
		<pose>Unspecified</pose>
		<truncated>0</truncated>
		<difficult>0</difficult>
		<bndbox>
			<xmin>294</xmin>
			<ymin>297</ymin>
			<xmax>344</xmax>
			<ymax>391</ymax>
		</bndbox>
	</object>
	<object>
		<name>car</name>
		<pose>Unspecified</pose>
		<truncated>0</truncated>
		<difficult>0</difficult>
		<bndbox>
			<xmin>262</xmin>
			<ymin>55</ymin>
			<xmax>283</xmax>
			<ymax>74</ymax>
		</bndbox>
	</object>
	<object>
		<name>car</name>
		<pose>Unspecified</pose>
		<truncated>0</truncated>
		<difficult>0</difficult>
		<bndbox>
			<xmin>287</xmin>
			<ymin>63</ymin>
			<xmax>313</xmax>
			<ymax>81</ymax>
		</bndbox>
	</object>
	<object>
		<name>car</name>
		<pose>Unspecified</pose>
		<truncated>0</truncated>
		<difficult>0</difficult>
		<bndbox>
			<xmin>337</xmin>
			<ymin>69</ymin>
			<xmax>360</xmax>
			<ymax>88</ymax>
		</bndbox>
	</object>
	<object>
		<name>car</name>
		<pose>Unspecified</pose>
		<truncated>0</truncated>
		<difficult>0</difficult>
		<bndbox>
			<xmin>448</xmin>
			<ymin>83</ymin>
			<xmax>476</xmax>
			<ymax>106</ymax>
		</bndbox>
	</object>
	<object>
		<name>car</name>
		<pose>Unspecified</pose>
		<truncated>0</truncated>
		<difficult>0</difficult>
		<bndbox>
			<xmin>564</xmin>
			<ymin>88</ymin>
			<xmax>594</xmax>
			<ymax>108</ymax>
		</bndbox>
	</object>
	<object>
		<name>car</name>
		<pose>Unspecified</pose>
		<truncated>0</truncated>
		<difficult>0</difficult>
		<bndbox>
			<xmin>149</xmin>
			<ymin>62</ymin>
			<xmax>172</xmax>
			<ymax>81</ymax>
		</bndbox>
	</object>
</annotation>
