<annotation>
	<folder>trafik uygulama foto</folder>
	<filename>image1411.jpg</filename>
	<path>C:\Users\ahmet\OneDrive\Masaüstü\tez\ikinci deneme\trafik uygulama foto\image1411.jpg</path>
	<source>
		<database>Unknown</database>
	</source>
	<size>
		<width>1920</width>
		<height>1080</height>
		<depth>3</depth>
	</size>
	<segmented>0</segmented>
	<object>
		<name>car</name>
		<pose>Unspecified</pose>
		<truncated>0</truncated>
		<difficult>0</difficult>
		<bndbox>
			<xmin>495</xmin>
			<ymin>565</ymin>
			<xmax>698</xmax>
			<ymax>727</ymax>
		</bndbox>
	</object>
	<object>
		<name>car</name>
		<pose>Unspecified</pose>
		<truncated>0</truncated>
		<difficult>0</difficult>
		<bndbox>
			<xmin>707</xmin>
			<ymin>549</ymin>
			<xmax>894</xmax>
			<ymax>782</ymax>
		</bndbox>
	</object>
	<object>
		<name>car</name>
		<pose>Unspecified</pose>
		<truncated>0</truncated>
		<difficult>0</difficult>
		<bndbox>
			<xmin>979</xmin>
			<ymin>550</ymin>
			<xmax>1136</xmax>
			<ymax>703</ymax>
		</bndbox>
	</object>
	<object>
		<name>car</name>
		<pose>Unspecified</pose>
		<truncated>0</truncated>
		<difficult>0</difficult>
		<bndbox>
			<xmin>920</xmin>
			<ymin>701</ymin>
			<xmax>1112</xmax>
			<ymax>947</ymax>
		</bndbox>
	</object>
	<object>
		<name>car</name>
		<pose>Unspecified</pose>
		<truncated>0</truncated>
		<difficult>0</difficult>
		<bndbox>
			<xmin>1188</xmin>
			<ymin>727</ymin>
			<xmax>1479</xmax>
			<ymax>1047</ymax>
		</bndbox>
	</object>
	<object>
		<name>car</name>
		<pose>Unspecified</pose>
		<truncated>0</truncated>
		<difficult>0</difficult>
		<bndbox>
			<xmin>227</xmin>
			<ymin>735</ymin>
			<xmax>538</xmax>
			<ymax>997</ymax>
		</bndbox>
	</object>
	<object>
		<name>car</name>
		<pose>Unspecified</pose>
		<truncated>0</truncated>
		<difficult>0</difficult>
		<bndbox>
			<xmin>613</xmin>
			<ymin>270</ymin>
			<xmax>772</xmax>
			<ymax>349</ymax>
		</bndbox>
	</object>
	<object>
		<name>car</name>
		<pose>Unspecified</pose>
		<truncated>0</truncated>
		<difficult>0</difficult>
		<bndbox>
			<xmin>745</xmin>
			<ymin>261</ymin>
			<xmax>895</xmax>
			<ymax>324</ymax>
		</bndbox>
	</object>
	<object>
		<name>car</name>
		<pose>Unspecified</pose>
		<truncated>0</truncated>
		<difficult>0</difficult>
		<bndbox>
			<xmin>975</xmin>
			<ymin>240</ymin>
			<xmax>1121</xmax>
			<ymax>310</ymax>
		</bndbox>
	</object>
	<object>
		<name>car</name>
		<pose>Unspecified</pose>
		<truncated>0</truncated>
		<difficult>0</difficult>
		<bndbox>
			<xmin>1161</xmin>
			<ymin>253</ymin>
			<xmax>1309</xmax>
			<ymax>315</ymax>
		</bndbox>
	</object>
	<object>
		<name>car</name>
		<pose>Unspecified</pose>
		<truncated>0</truncated>
		<difficult>0</difficult>
		<bndbox>
			<xmin>1330</xmin>
			<ymin>200</ymin>
			<xmax>1432</xmax>
			<ymax>246</ymax>
		</bndbox>
	</object>
	<object>
		<name>car</name>
		<pose>Unspecified</pose>
		<truncated>0</truncated>
		<difficult>0</difficult>
		<bndbox>
			<xmin>1759</xmin>
			<ymin>158</ymin>
			<xmax>1845</xmax>
			<ymax>192</ymax>
		</bndbox>
	</object>
	<object>
		<name>car</name>
		<pose>Unspecified</pose>
		<truncated>0</truncated>
		<difficult>0</difficult>
		<bndbox>
			<xmin>840</xmin>
			<ymin>113</ymin>
			<xmax>906</xmax>
			<ymax>149</ymax>
		</bndbox>
	</object>
	<object>
		<name>car</name>
		<pose>Unspecified</pose>
		<truncated>0</truncated>
		<difficult>0</difficult>
		<bndbox>
			<xmin>175</xmin>
			<ymin>144</ymin>
			<xmax>265</xmax>
			<ymax>188</ymax>
		</bndbox>
	</object>
	<object>
		<name>car</name>
		<pose>Unspecified</pose>
		<truncated>0</truncated>
		<difficult>0</difficult>
		<bndbox>
			<xmin>1377</xmin>
			<ymin>163</ymin>
			<xmax>1477</xmax>
			<ymax>197</ymax>
		</bndbox>
	</object>
</annotation>
