<annotation>
	<folder>bizim fotolar</folder>
	<filename>IMG_20200314_132945.jpg</filename>
	<path>C:\Users\ahmet\OneDrive\Masaüstü\bizim fotolar\IMG_20200314_132945.jpg</path>
	<source>
		<database>Unknown</database>
	</source>
	<size>
		<width>5120</width>
		<height>3840</height>
		<depth>3</depth>
	</size>
	<segmented>0</segmented>
	<object>
		<name>person</name>
		<pose>Unspecified</pose>
		<truncated>0</truncated>
		<difficult>0</difficult>
		<bndbox>
			<xmin>2093</xmin>
			<ymin>107</ymin>
			<xmax>2147</xmax>
			<ymax>236</ymax>
		</bndbox>
	</object>
	<object>
		<name>person</name>
		<pose>Unspecified</pose>
		<truncated>0</truncated>
		<difficult>0</difficult>
		<bndbox>
			<xmin>2051</xmin>
			<ymin>90</ymin>
			<xmax>2097</xmax>
			<ymax>257</ymax>
		</bndbox>
	</object>
	<object>
		<name>person</name>
		<pose>Unspecified</pose>
		<truncated>0</truncated>
		<difficult>0</difficult>
		<bndbox>
			<xmin>2235</xmin>
			<ymin>2278</ymin>
			<xmax>2430</xmax>
			<ymax>2870</ymax>
		</bndbox>
	</object>
	<object>
		<name>person</name>
		<pose>Unspecified</pose>
		<truncated>0</truncated>
		<difficult>0</difficult>
		<bndbox>
			<xmin>2472</xmin>
			<ymin>2262</ymin>
			<xmax>2697</xmax>
			<ymax>2791</ymax>
		</bndbox>
	</object>
	<object>
		<name>person</name>
		<pose>Unspecified</pose>
		<truncated>0</truncated>
		<difficult>0</difficult>
		<bndbox>
			<xmin>2755</xmin>
			<ymin>2303</ymin>
			<xmax>2985</xmax>
			<ymax>2866</ymax>
		</bndbox>
	</object>
</annotation>
