<annotation>
	<folder>images</folder>
	<filename>472.jpg</filename>
	<path>C:\Users\ahmet\OneDrive\Masaüstü\tez\ikinci deneme\600-600\data\images\472.jpg</path>
	<source>
		<database>Unknown</database>
	</source>
	<size>
		<width>600</width>
		<height>600</height>
		<depth>3</depth>
	</size>
	<segmented>0</segmented>
	<object>
		<name>car</name>
		<pose>Unspecified</pose>
		<truncated>0</truncated>
		<difficult>0</difficult>
		<bndbox>
			<xmin>103</xmin>
			<ymin>349</ymin>
			<xmax>181</xmax>
			<ymax>458</ymax>
		</bndbox>
	</object>
	<object>
		<name>car</name>
		<pose>Unspecified</pose>
		<truncated>0</truncated>
		<difficult>0</difficult>
		<bndbox>
			<xmin>151</xmin>
			<ymin>432</ymin>
			<xmax>234</xmax>
			<ymax>570</ymax>
		</bndbox>
	</object>
	<object>
		<name>car</name>
		<pose>Unspecified</pose>
		<truncated>0</truncated>
		<difficult>0</difficult>
		<bndbox>
			<xmin>200</xmin>
			<ymin>341</ymin>
			<xmax>260</xmax>
			<ymax>432</ymax>
		</bndbox>
	</object>
	<object>
		<name>car</name>
		<pose>Unspecified</pose>
		<truncated>0</truncated>
		<difficult>0</difficult>
		<bndbox>
			<xmin>282</xmin>
			<ymin>270</ymin>
			<xmax>370</xmax>
			<ymax>541</ymax>
		</bndbox>
	</object>
	<object>
		<name>car</name>
		<pose>Unspecified</pose>
		<truncated>0</truncated>
		<difficult>0</difficult>
		<bndbox>
			<xmin>293</xmin>
			<ymin>123</ymin>
			<xmax>338</xmax>
			<ymax>159</ymax>
		</bndbox>
	</object>
	<object>
		<name>car</name>
		<pose>Unspecified</pose>
		<truncated>0</truncated>
		<difficult>0</difficult>
		<bndbox>
			<xmin>225</xmin>
			<ymin>115</ymin>
			<xmax>263</xmax>
			<ymax>151</ymax>
		</bndbox>
	</object>
	<object>
		<name>car</name>
		<pose>Unspecified</pose>
		<truncated>0</truncated>
		<difficult>0</difficult>
		<bndbox>
			<xmin>367</xmin>
			<ymin>127</ymin>
			<xmax>410</xmax>
			<ymax>159</ymax>
		</bndbox>
	</object>
	<object>
		<name>car</name>
		<pose>Unspecified</pose>
		<truncated>0</truncated>
		<difficult>0</difficult>
		<bndbox>
			<xmin>462</xmin>
			<ymin>105</ymin>
			<xmax>495</xmax>
			<ymax>131</ymax>
		</bndbox>
	</object>
	<object>
		<name>car</name>
		<pose>Unspecified</pose>
		<truncated>0</truncated>
		<difficult>0</difficult>
		<bndbox>
			<xmin>492</xmin>
			<ymin>117</ymin>
			<xmax>526</xmax>
			<ymax>144</ymax>
		</bndbox>
	</object>
	<object>
		<name>car</name>
		<pose>Unspecified</pose>
		<truncated>0</truncated>
		<difficult>0</difficult>
		<bndbox>
			<xmin>479</xmin>
			<ymin>85</ymin>
			<xmax>507</xmax>
			<ymax>102</ymax>
		</bndbox>
	</object>
	<object>
		<name>car</name>
		<pose>Unspecified</pose>
		<truncated>0</truncated>
		<difficult>0</difficult>
		<bndbox>
			<xmin>561</xmin>
			<ymin>89</ymin>
			<xmax>591</xmax>
			<ymax>107</ymax>
		</bndbox>
	</object>
	<object>
		<name>car</name>
		<pose>Unspecified</pose>
		<truncated>0</truncated>
		<difficult>0</difficult>
		<bndbox>
			<xmin>287</xmin>
			<ymin>75</ymin>
			<xmax>317</xmax>
			<ymax>98</ymax>
		</bndbox>
	</object>
	<object>
		<name>car</name>
		<pose>Unspecified</pose>
		<truncated>0</truncated>
		<difficult>0</difficult>
		<bndbox>
			<xmin>437</xmin>
			<ymin>86</ymin>
			<xmax>464</xmax>
			<ymax>105</ymax>
		</bndbox>
	</object>
</annotation>
