<annotation>
	<folder>yeni fotolar</folder>
	<filename>image1051.jpg</filename>
	<path>C:\Users\Casper\Desktop\yeni fotolar\image1051.jpg</path>
	<source>
		<database>Unknown</database>
	</source>
	<size>
		<width>1920</width>
		<height>1080</height>
		<depth>3</depth>
	</size>
	<segmented>0</segmented>
	<object>
		<name>person</name>
		<pose>Unspecified</pose>
		<truncated>0</truncated>
		<difficult>0</difficult>
		<bndbox>
			<xmin>1559</xmin>
			<ymin>392</ymin>
			<xmax>1631</xmax>
			<ymax>529</ymax>
		</bndbox>
	</object>
	<object>
		<name>person</name>
		<pose>Unspecified</pose>
		<truncated>0</truncated>
		<difficult>0</difficult>
		<bndbox>
			<xmin>984</xmin>
			<ymin>192</ymin>
			<xmax>1025</xmax>
			<ymax>239</ymax>
		</bndbox>
	</object>
	<object>
		<name>car</name>
		<pose>Unspecified</pose>
		<truncated>0</truncated>
		<difficult>0</difficult>
		<bndbox>
			<xmin>198</xmin>
			<ymin>757</ymin>
			<xmax>594</xmax>
			<ymax>1049</ymax>
		</bndbox>
	</object>
	<object>
		<name>car</name>
		<pose>Unspecified</pose>
		<truncated>0</truncated>
		<difficult>0</difficult>
		<bndbox>
			<xmin>514</xmin>
			<ymin>237</ymin>
			<xmax>700</xmax>
			<ymax>321</ymax>
		</bndbox>
	</object>
	<object>
		<name>car</name>
		<pose>Unspecified</pose>
		<truncated>0</truncated>
		<difficult>0</difficult>
		<bndbox>
			<xmin>72</xmin>
			<ymin>263</ymin>
			<xmax>273</xmax>
			<ymax>323</ymax>
		</bndbox>
	</object>
</annotation>
