<annotation>
	<folder>resimler</folder>
	<filename>image55.jpg</filename>
	<path>C:\Users\casper\Desktop\resimler\image55.jpg</path>
	<source>
		<database>Unknown</database>
	</source>
	<size>
		<width>1920</width>
		<height>1080</height>
		<depth>3</depth>
	</size>
	<segmented>0</segmented>
	<object>
		<name>person</name>
		<pose>Unspecified</pose>
		<truncated>0</truncated>
		<difficult>0</difficult>
		<bndbox>
			<xmin>1362</xmin>
			<ymin>329</ymin>
			<xmax>1408</xmax>
			<ymax>422</ymax>
		</bndbox>
	</object>
	<object>
		<name>person</name>
		<pose>Unspecified</pose>
		<truncated>0</truncated>
		<difficult>0</difficult>
		<bndbox>
			<xmin>1594</xmin>
			<ymin>307</ymin>
			<xmax>1650</xmax>
			<ymax>391</ymax>
		</bndbox>
	</object>
	<object>
		<name>car</name>
		<pose>Unspecified</pose>
		<truncated>0</truncated>
		<difficult>0</difficult>
		<bndbox>
			<xmin>498</xmin>
			<ymin>499</ymin>
			<xmax>697</xmax>
			<ymax>682</ymax>
		</bndbox>
	</object>
	<object>
		<name>car</name>
		<pose>Unspecified</pose>
		<truncated>0</truncated>
		<difficult>0</difficult>
		<bndbox>
			<xmin>709</xmin>
			<ymin>329</ymin>
			<xmax>830</xmax>
			<ymax>432</ymax>
		</bndbox>
	</object>
	<object>
		<name>car</name>
		<pose>Unspecified</pose>
		<truncated>0</truncated>
		<difficult>0</difficult>
		<bndbox>
			<xmin>595</xmin>
			<ymin>220</ymin>
			<xmax>765</xmax>
			<ymax>313</ymax>
		</bndbox>
	</object>
	<object>
		<name>car</name>
		<pose>Unspecified</pose>
		<truncated>0</truncated>
		<difficult>0</difficult>
		<bndbox>
			<xmin>435</xmin>
			<ymin>250</ymin>
			<xmax>555</xmax>
			<ymax>343</ymax>
		</bndbox>
	</object>
	<object>
		<name>car</name>
		<pose>Unspecified</pose>
		<truncated>0</truncated>
		<difficult>0</difficult>
		<bndbox>
			<xmin>54</xmin>
			<ymin>223</ymin>
			<xmax>207</xmax>
			<ymax>303</ymax>
		</bndbox>
	</object>
	<object>
		<name>car</name>
		<pose>Unspecified</pose>
		<truncated>0</truncated>
		<difficult>0</difficult>
		<bndbox>
			<xmin>108</xmin>
			<ymin>99</ymin>
			<xmax>202</xmax>
			<ymax>162</ymax>
		</bndbox>
	</object>
	<object>
		<name>car</name>
		<pose>Unspecified</pose>
		<truncated>0</truncated>
		<difficult>0</difficult>
		<bndbox>
			<xmin>227</xmin>
			<ymin>81</ymin>
			<xmax>325</xmax>
			<ymax>141</ymax>
		</bndbox>
	</object>
	<object>
		<name>car</name>
		<pose>Unspecified</pose>
		<truncated>0</truncated>
		<difficult>0</difficult>
		<bndbox>
			<xmin>477</xmin>
			<ymin>104</ymin>
			<xmax>564</xmax>
			<ymax>155</ymax>
		</bndbox>
	</object>
	<object>
		<name>car</name>
		<pose>Unspecified</pose>
		<truncated>0</truncated>
		<difficult>0</difficult>
		<bndbox>
			<xmin>1521</xmin>
			<ymin>150</ymin>
			<xmax>1627</xmax>
			<ymax>191</ymax>
		</bndbox>
	</object>
</annotation>
